MANIFEST.in
setup.py
ListMilestonesMacro.egg-info/PKG-INFO
ListMilestonesMacro.egg-info/SOURCES.txt
ListMilestonesMacro.egg-info/dependency_links.txt
ListMilestonesMacro.egg-info/entry_points.txt
ListMilestonesMacro.egg-info/not-zip-safe
ListMilestonesMacro.egg-info/top_level.txt
listmilestones/__init__.py
listmilestones/api.py
listmilestones/templates/listmilestones.html