Metadata-Version: 1.0
Name: ListMilestonesMacro
Version: 0.1.2
Summary: Lists milestones based on a name.
Home-page: http://mitar.tnode.com/
Author: Mitar
Author-email: mitar.trac@tnode.com
License: AGPLv3
Keywords: trac plugin
Platform: UNKNOWN
